[
    {
        "title": "Donald Trump hasn’t tweeted in 19 hours, what are your theories on what’s happening in the White House right now?",
        "url": "https://www.reddit.com/r/AskReddit/comments/b4kww0/donald_trump_hasnt_tweeted_in_19_hours_what_are/",
        "author": "lovescatsandthings"
    },
    {
        "title": "Over 1 million march in London for a second referendum",
        "url": "https://news.sky.com/story/live-hundreds-of-thousands-set-to-march-in-peoples-vote-call-for-second-referendum-11673263",
        "author": "simon1828"
    },
    {
        "title": "Yikes.",
        "url": "https://i.redd.it/sxvo176h2yn21.jpg",
        "author": "the7aco"
    },
    {
        "title": "I do NOT want real cheese!!!",
        "url": "https://i.redd.it/ynqpqp6mlvn21.png",
        "author": "offbrandhandjobs"
    },
    {
        "title": "I like to eat freezer meals still frozen",
        "url": "https://www.reddit.com/r/unpopularopinion/comments/b4ov0l/i_like_to_eat_freezer_meals_still_frozen/",
        "author": "Gabeoobla"
    },
    {
        "title": "I guess Asexuals aren't queer enough?",
        "url": "https://i.redd.it/kqvvi55vnvn21.jpg",
        "author": "Spaced_Out_Ace"
    },
    {
        "title": "Yea that makes sense right?",
        "url": "https://i.redd.it/etzg1jczoxn21.jpg",
        "author": "glorious_bangla"
    },
    {
        "title": "TIL that when 13-year-old Ryan White got AIDS from a blood donor in 1984, he was banned from returning to school by a petition signed by 117 parents. An auction was held to keep him out, a newspaper supporting him got death threats, and his family left town when a gun was fired through their window.",
        "url": "https://en.wikipedia.org/wiki/Ryan_White",
        "author": "IHad360K_KarmaDammit"
    },
    {
        "title": "How Burger King deals with bad customers.. that bitch slap tho",
        "url": "https://v.redd.it/8gzd3mr5dun21",
        "author": "hiftikha"
    },
    {
        "title": "Someone took the Harry Potter theme of the bridal shower a bit too seriously",
        "url": "https://i.redd.it/i5p7yjufpxn21.jpg",
        "author": "chpbnvic"
    },
    {
        "title": "British citizens protesting against leaving the European Union, London",
        "url": "https://imgur.com/Etie19Q",
        "author": "Blithe17"
    },
    {
        "title": "A banner at the pro-EU march in London where one million people have turned out to protest",
        "url": "https://i.redd.it/updwjk33jwn21.jpg",
        "author": "DisunitedKingdom"
    },
    {
        "title": "Shades of...everything",
        "url": "https://i.redd.it/0miki3kpkxn21.jpg",
        "author": "diablek"
    },
    {
        "title": "Well, when you put it that way...",
        "url": "https://i.redd.it/vrojormmfxn21.jpg",
        "author": "Panzermoosen"
    },
    {
        "title": "Royal Navy officer caught on tape: “no such thing as mental health”",
        "url": "https://militarynews.co.uk/2019/03/22/royal-navy-officer-caught-on-tape-no-such-thing-as-mental-health/",
        "author": "Oriachim"
    },
    {
        "title": "Momma was exhausted from taking care of the pups so dad went to get her a snack",
        "url": "https://i.imgur.com/feDZXjZ.gifv",
        "author": "MyNameGifOreilly"
    },
    {
        "title": "Kicking a water balloon",
        "url": "https://v.redd.it/ijheui6ozxn21",
        "author": "HusseinRazak"
    },
    {
        "title": "Marvel’s First Family",
        "url": "https://i.redd.it/mnlya38bkvn21.jpg",
        "author": "Zosodechaine"
    },
    {
        "title": "I'm a hearing student attending the only deaf university in the world. Ask me anything! 😃",
        "url": "https://www.reddit.com/r/IAmA/comments/b4mtkc/im_a_hearing_student_attending_the_only_deaf/",
        "author": "Hero_Prinny"
    },
    {
        "title": "The best video game episode television has ever seen",
        "url": "https://i.imgur.com/COUdjf9.jpg",
        "author": "juul_pod"
    },
    {
        "title": "My big dangerous Rottweiler with my baby hamster",
        "url": "https://i.redd.it/aiapt0wjmxn21.jpg",
        "author": "necele"
    },
    {
        "title": "Guys who have their stuff together, but won't commit, what's your story?",
        "url": "https://www.reddit.com/r/AskMen/comments/b4ijof/guys_who_have_their_stuff_together_but_wont/",
        "author": "coldcerealdater"
    },
    {
        "title": "Majority of bitcoin trading is a hoax, new study finds",
        "url": "https://www.cnbc.com/2019/03/22/majority-of-bitcoin-trading-is-a-hoax-new-study-finds.html",
        "author": "Kgvdj860m"
    },
    {
        "title": "My lamp spells \"Anal\" on the wall",
        "url": "https://i.redd.it/7uqijj1uhyn21.jpg",
        "author": "maddafakk"
    },
    {
        "title": "Seemed like a 5 star man",
        "url": "https://i.redd.it/zi0o5mnfown21.jpg",
        "author": "MrWap"
    }
]